decapitate_the_spire/__init__.py
decapitate_the_spire/__main__.py
decapitate_the_spire/decapitate_the_spire.py
decapitate_the_spire/game.py
decapitate_the_spire/rng.py
test/__init__.py
test/dungeon_test_case.py
test/test_decapitate_the_spire.py
test/test_game.py
test/test_mini_dungeon.py
test/test_utils.py
decapitate_the_spire-0.2.0.dist-info/LICENSE
decapitate_the_spire-0.2.0.dist-info/METADATA
decapitate_the_spire-0.2.0.dist-info/WHEEL
decapitate_the_spire-0.2.0.dist-info/top_level.txt
decapitate_the_spire-0.2.0.dist-info/RECORD
