Metadata-Version: 2.1
Name: decapitate-the-spire
Version: 0.2.0
Summary: A headless clone of Mega Crit's Slay the Spire
Home-page: https://github.com/jahabrewer/decapitate-the-spire
Author: Janzen Brewer-Krebs
Author-email: janzen@toypiper.com
License: UNKNOWN
Platform: UNKNOWN
Classifier: Development Status :: 2 - Pre-Alpha
Classifier: Topic :: Games/Entertainment
Classifier: License :: OSI Approved :: GNU General Public License v3 (GPLv3)
Classifier: Programming Language :: Python :: 3
Classifier: Operating System :: OS Independent
License-File: LICENSE
